groupbuyorganizer/__init__.py
groupbuyorganizer/admin/__init__.py
groupbuyorganizer/admin/forms.py
groupbuyorganizer/admin/models.py
groupbuyorganizer/admin/routes.py
groupbuyorganizer/admin/utilities.py
groupbuyorganizer/errors/__init__.py
groupbuyorganizer/errors/handlers.py
groupbuyorganizer/events/__init__.py
groupbuyorganizer/events/forms.py
groupbuyorganizer/events/models.py
groupbuyorganizer/events/routes.py
groupbuyorganizer/events/utility_functions.py
groupbuyorganizer/events/utility_objects.py
groupbuyorganizer/general/__init__.py
groupbuyorganizer/general/forms.py
groupbuyorganizer/general/routes.py
venv/Lib/site-packages/easy_install.py
venv/Lib/site-packages/flask_bcrypt.py
venv/Lib/site-packages/flask_mail.py
venv/Lib/site-packages/flask_principal.py
venv/Lib/site-packages/mock.py
venv/Lib/site-packages/six.py
venv/Lib/site-packages/speaklater.py
venv/Lib/site-packages/babel/__init__.py
venv/Lib/site-packages/babel/_compat.py
venv/Lib/site-packages/babel/core.py
venv/Lib/site-packages/babel/dates.py
venv/Lib/site-packages/babel/languages.py
venv/Lib/site-packages/babel/lists.py
venv/Lib/site-packages/babel/localedata.py
venv/Lib/site-packages/babel/numbers.py
venv/Lib/site-packages/babel/plural.py
venv/Lib/site-packages/babel/support.py
venv/Lib/site-packages/babel/units.py
venv/Lib/site-packages/babel/util.py
venv/Lib/site-packages/babel/localtime/__init__.py
venv/Lib/site-packages/babel/localtime/_unix.py
venv/Lib/site-packages/babel/localtime/_win32.py
venv/Lib/site-packages/babel/messages/__init__.py
venv/Lib/site-packages/babel/messages/catalog.py
venv/Lib/site-packages/babel/messages/checkers.py
venv/Lib/site-packages/babel/messages/extract.py
venv/Lib/site-packages/babel/messages/frontend.py
venv/Lib/site-packages/babel/messages/jslexer.py
venv/Lib/site-packages/babel/messages/mofile.py
venv/Lib/site-packages/babel/messages/plurals.py
venv/Lib/site-packages/babel/messages/pofile.py
venv/Lib/site-packages/bcrypt/__about__.py
Group_Buy_Organizer-1.0.3.dist-info/LICENSE
Group_Buy_Organizer-1.0.3.dist-info/METADATA
Group_Buy_Organizer-1.0.3.dist-info/WHEEL
Group_Buy_Organizer-1.0.3.dist-info/top_level.txt
Group_Buy_Organizer-1.0.3.dist-info/RECORD
