Metadata-Version: 2.1
Name: Group-Buy-Organizer
Version: 1.0.3
Summary: 📦 Quickly coordinate large wholesale group orders with this easy to use web app.
Home-page: https://github.com/MarkMichon1/Group-Buy-Organizer
Author: Mark Michon
Author-email: markmichon7@gmail.com
License: UNKNOWN
Platform: UNKNOWN
Classifier: Programming Language :: Python :: 3.7
Classifier: License :: OSI Approved :: MIT License
Classifier: Operating System :: OS Independent
Requires-Dist: flask
Requires-Dist: flask-bcrypt
Requires-Dist: flask-login
Requires-Dist: flask-sqlalchemy
Requires-Dist: flask-wtf
Requires-Dist: pdfkit
